extract_yt_url/__init__.py
extract_yt_url-0.0.1.dist-info/METADATA
extract_yt_url-0.0.1.dist-info/WHEEL
extract_yt_url-0.0.1.dist-info/top_level.txt
extract_yt_url-0.0.1.dist-info/RECORD
